golemcpp/__init__.py
golemcpp/data/clangd.template
golemcpp/data/wscript
golemcpp/golem/__init__.py
golemcpp/golem/__main__.py
golemcpp/golem/artifact.py
golemcpp/golem/build_target.py
golemcpp/golem/builder.py
golemcpp/golem/cache.py
golemcpp/golem/condition.py
golemcpp/golem/condition_expression.py
golemcpp/golem/configuration.py
golemcpp/golem/context.py
golemcpp/golem/dependency.py
golemcpp/golem/helpers.py
golemcpp/golem/main.py
golemcpp/golem/module.py
golemcpp/golem/package.py
golemcpp/golem/package_dmg.py
golemcpp/golem/package_msi.py
golemcpp/golem/project.py
golemcpp/golem/target.py
golemcpp/golem/template.py
golemcpp/golem/version.py
golemcpp-1.0.3.dist-info/licenses/LICENSE
golemcpp-1.0.3.dist-info/WHEEL
golemcpp-1.0.3.dist-info/entry_points.txt
golemcpp-1.0.3.dist-info/METADATA
golemcpp-1.0.3.dist-info/RECORD
