Metadata-Version: 2.4
Name: golemcpp
Version: 1.0.3
Summary: Golem is a cross-platform build system for C/C++ projects
Keywords: cpp
Author: Barnabé BALP
Author-email: Barnabé BALP <contact@barnabebalp.fr>
License-Expression: MIT
License-File: LICENSE
Classifier: Programming Language :: Python :: 3
Classifier: Operating System :: OS Independent
Requires-Dist: golemcpp-waflib==1.0.3
Requires-Dist: node-semver==0.8.0
Requires-Python: >=3.10
Project-URL: Documentation, https://github.com/GolemCpp/golem
Project-URL: Homepage, https://github.com/GolemCpp/golem
Project-URL: Issues, https://github.com/GolemCpp/golem/issues
Project-URL: Repository, https://github.com/GolemCpp/golem.git
